nodequery
